RenjiBianjieZhonggouGongyeZhinengMaixiangGuimohuaDeYinbaoDianFix1/README.md
RenjiBianjieZhonggouGongyeZhinengMaixiangGuimohuaDeYinbaoDianFix1/__init__.py
RenjiBianjieZhonggouGongyeZhinengMaixiangGuimohuaDeYinbaoDianFix1/__main__.py
RenjiBianjieZhonggouGongyeZhinengMaixiangGuimohuaDeYinbaoDianFix1/file.pdf
RenjiBianjieZhonggouGongyeZhinengMaixiangGuimohuaDeYinbaoDianFix1/index.html
renji_bianjie_zhonggou_gongye_zhineng_maixiang_guimohua_de_yinbao_dian_fix1-2025.3.24.0.dist-info/METADATA
renji_bianjie_zhonggou_gongye_zhineng_maixiang_guimohua_de_yinbao_dian_fix1-2025.3.24.0.dist-info/WHEEL
renji_bianjie_zhonggou_gongye_zhineng_maixiang_guimohua_de_yinbao_dian_fix1-2025.3.24.0.dist-info/entry_points.txt
renji_bianjie_zhonggou_gongye_zhineng_maixiang_guimohua_de_yinbao_dian_fix1-2025.3.24.0.dist-info/top_level.txt
renji_bianjie_zhonggou_gongye_zhineng_maixiang_guimohua_de_yinbao_dian_fix1-2025.3.24.0.dist-info/RECORD
